iroha2-0.1.1.dist-info/METADATA
iroha2-0.1.1.dist-info/WHEEL
iroha2-0.1.1.dist-info/licenses/LICENSE
iroha2/__init__.py
iroha2/iroha2.cpython-38-x86_64-linux-gnu.so
iroha2-0.1.1.dist-info/RECORD
