Metadata-Version: 2.3
Name: iroha2
Version: 0.1.1
Classifier: Programming Language :: Rust
Classifier: Programming Language :: Python :: Implementation :: CPython
Classifier: Programming Language :: Python :: Implementation :: PyPy
Requires-Dist: fixedint ==0.2.0
License-File: LICENSE
Requires-Python: >=3.7
